great_ai/__init__.py
great_ai/__main__.py
great_ai/constants.py
great_ai/context.py
great_ai/parse_arguments.py
great_ai/deploy/__init__.py
great_ai/deploy/great_ai.py
great_ai/deploy/routes/__init__.py
great_ai/deploy/routes/bootstrap_dashboard.py
great_ai/deploy/routes/bootstrap_docs_endpoints.py
great_ai/deploy/routes/bootstrap_feedback_endpoints.py
great_ai/deploy/routes/bootstrap_meta_endpoints.py
great_ai/deploy/routes/bootstrap_prediction_endpoint.py
great_ai/deploy/routes/bootstrap_trace_endpoints.py
great_ai/deploy/routes/dashboard/__init__.py
great_ai/deploy/routes/dashboard/create_dash_app.py
great_ai/deploy/routes/dashboard/get_description.py
great_ai/deploy/routes/dashboard/get_filter_from_datatable.py
great_ai/deploy/routes/dashboard/get_footer.py
great_ai/deploy/routes/dashboard/get_traces_table.py
great_ai/deploy/routes/dashboard/assets/favicon.ico
great_ai/deploy/routes/dashboard/assets/index.css
great_ai/deploy/routes/dashboard/assets/logo.png
great_ai/deploy/routes/dashboard/assets/logo.svg
great_ai/errors/__init__.py
great_ai/errors/argument_validation_error.py
great_ai/errors/missing_argument_error.py
great_ai/errors/remote_call_error.py
great_ai/errors/wrong_decorator_order_error.py
great_ai/external/__init__.py
great_ai/external/async_lru.py
great_ai/helper/__init__.py
great_ai/helper/assert_function_is_not_finalised.py
great_ai/helper/freeze_arguments.py
great_ai/helper/get_arguments.py
great_ai/helper/get_function_metadata_store.py
great_ai/helper/snake_case_to_text.py
great_ai/helper/strip_lines.py
great_ai/helper/text_to_hex_color.py
great_ai/large_file/__init__.py
great_ai/large_file/__main__.py
great_ai/large_file/parse_arguments.py
great_ai/large_file/helper/__init__.py
great_ai/large_file/helper/bytes_to_megabytes.py
great_ai/large_file/helper/cached_property.py
great_ai/large_file/helper/human_readable_to_byte.py
great_ai/large_file/helper/progress_bar.py
great_ai/large_file/large_file/__init__.py
sis_great_ai-0.1.18.dist-info/entry_points.txt
sis_great_ai-0.1.18.dist-info/LICENSE
sis_great_ai-0.1.18.dist-info/WHEEL
sis_great_ai-0.1.18.dist-info/METADATA
sis_great_ai-0.1.18.dist-info/RECORD
