Metadata-Version: 2.1
Name: sis-great-ai
Version: 0.1.18
Summary: Transform your prototype AI code into production-ready software.
Keywords: SE4ML,MLOps,AI engineering,general,robust,end-to-end,automated,trustworthy,ai,deployment
Author-email: András Schmelczer <andras@schmelczer.dev>
Requires-Python: >= 3.7
Classifier: Operating System :: OS Independent
Classifier: Programming Language :: Python :: 3
Classifier: Topic :: Software Development :: Libraries :: Python Modules
Classifier: Typing :: Typed
Classifier: Development Status :: 3 - Alpha
Classifier: License :: OSI Approved :: GNU General Public License v3 or later (GPLv3+)
Classifier: Natural Language :: English
Requires-Dist: scikit-learn
Requires-Dist: matplotlib
Requires-Dist: numpy
Requires-Dist: nbconvert
Requires-Dist: ipython
Requires-Dist: unidecode >= 1.3.0
Requires-Dist: syntok >= 1.4.0
Requires-Dist: langcodes[data] >= 3.3.0
Requires-Dist: langdetect >= 1.0.9
Requires-Dist: tinydb >= 4.7.0
Requires-Dist: boto3 >= 1.23.0
Requires-Dist: plotly >= 5.8.0
Requires-Dist: pandas
Requires-Dist: dash >= 2.14.1
Requires-Dist: Werkzeug == 2.2.2
Requires-Dist: fastapi == 0.70.0
Requires-Dist: uvicorn[standard] >= 0.18.0
Requires-Dist: watchdog >= 2.1.0
Requires-Dist: typeguard >= 2.10.0
Requires-Dist: pymongo >= 4.0.0
Requires-Dist: dill >= 0.3.5.0
Requires-Dist: tqdm
Requires-Dist: httpx >= 0.20.0
Requires-Dist: flit ; extra == "dev"
Requires-Dist: mkdocs ; extra == "dev"
Requires-Dist: mkdocstrings[python] ; extra == "dev"
Requires-Dist: mkdocs-material ; extra == "dev"
Requires-Dist: mkdocs-jupyter ; extra == "dev"
Requires-Dist: mkdocs-git-revision-date-localized-plugin ; extra == "dev"
Requires-Dist: autoflake ; extra == "dev"
Requires-Dist: isort ; extra == "dev"
Requires-Dist: black[jupyter] ; extra == "dev"
Requires-Dist: mypy ; extra == "dev"
Requires-Dist: flake8 ; extra == "dev"
Requires-Dist: tox ; extra == "dev"
Requires-Dist: pytest ; extra == "dev"
Requires-Dist: pytest-cov ; extra == "dev"
Requires-Dist: pytest-asyncio ; extra == "dev"
Project-URL: DockerHub, https://hub.docker.com/repository/docker/scoutinscience/great-ai
Project-URL: Documentation, https://great-ai.scoutinscience.com
Project-URL: GitHub, https://github.com/scoutinscience/great-ai
Provides-Extra: dev
